LICENSE
README.md
setup.py
autoqubo/__init__.py
autoqubo/_package_info.py
autoqubo/binarization.py
autoqubo/penalty_weights.py
autoqubo/sampling_compiler.py
autoqubo/search_space.py
autoqubo/symbolic.py
autoqubo/utils.py
autoqubo.egg-info/PKG-INFO
autoqubo.egg-info/SOURCES.txt
autoqubo.egg-info/dependency_links.txt
autoqubo.egg-info/requires.txt
autoqubo.egg-info/top_level.txt
tests/test_binarization.py
tests/test_sampling_compiler.py
tests/test_search_space.py
tests/test_utils.py