Metadata-Version: 2.1
Name: autoqubo
Version: 0.0.3
Summary: AutoQUBO gives you the tools for creating QUBO from Python code.
Home-page: https://github.com/FujitsuResearch/autoqubo
Author: Fujitsu Limited
Author-email: 
Maintainer: Fujitsu Limited
Maintainer-email: 
License: BSD-3-Clause
Keywords: QUBO
Classifier: Programming Language :: Python :: 3
Classifier: Programming Language :: Python :: 3.3
Classifier: Programming Language :: Python :: 3.4
Classifier: Programming Language :: Python :: 3.5
Classifier: Programming Language :: Python :: 3.6
Classifier: Programming Language :: Python :: 3.7
Classifier: License :: OSI Approved :: BSD License
Requires-Python: !=3.0.*,!=3.1.*,!=3.2.*,!=3.3.*
License-File: LICENSE
Requires-Dist: numpy<2.0.0,>=1.14.0
Requires-Dist: sympy
Requires-Dist: typing-extensions
